freak/__init__.py
freak/_version.py
freak/freak.py
freak/py.typed
freak/uvicorn_threaded.py
freak-0.0.2.dist-info/LICENSE.md
freak-0.0.2.dist-info/METADATA
freak-0.0.2.dist-info/WHEEL
freak-0.0.2.dist-info/RECORD
