Metadata-Version: 2.1
Name: freak
Version: 0.0.2
Summary: Remote application state control
Home-page: https://github.com/danielgafni/freak
License: MIT
Keywords: state,control,remote,application
Author: Daniel Gafni
Author-email: danielgafni16@gmail.com
Requires-Python: >=3.8,<4.0
Classifier: License :: OSI Approved :: MIT License
Classifier: Programming Language :: Python :: 3
Classifier: Programming Language :: Python :: 3.8
Classifier: Programming Language :: Python :: 3.9
Classifier: Programming Language :: Python :: 3.10
Classifier: Programming Language :: Python :: 3.11
Classifier: Programming Language :: Python :: 3.10
Classifier: Programming Language :: Python :: 3.11
Classifier: Programming Language :: Python :: 3.8
Classifier: Programming Language :: Python :: 3.9
Classifier: Topic :: Software Development :: Libraries :: Python Modules
Classifier: Topic :: Utilities
Requires-Dist: fastapi
Requires-Dist: uvicorn
Project-URL: Repository, https://github.com/danielgafni/freak
